kakashi/__init__.py
kakashi/fallback.py
kakashi/core/__init__.py
kakashi/core/async_backend.py
kakashi/core/async_interface.py
kakashi/core/async_pipeline.py
kakashi/core/config.py
kakashi/core/functional_logger.py
kakashi/core/interface.py
kakashi/core/logger.py
kakashi/core/pipeline.py
kakashi/core/records.py
kakashi/core/sink_config.py
kakashi/core/sink_pipeline.py
kakashi/core/sinks.py
kakashi/core/structured_async_backend.py
kakashi/core/structured_formatters.py
kakashi/core/structured_logger.py
kakashi/examples/__init__.py
kakashi/examples/basic_usage.py
kakashi/examples/cli_application_example.py
kakashi/examples/gui_application_example.py
kakashi/examples/web_framework_examples.py
kakashi/integrations/__init__.py
kakashi/integrations/django_integration.py
kakashi/integrations/fastapi_integration.py
kakashi/integrations/flask_integration.py
kakashi-0.2.0.dist-info/licenses/LICENSE
kakashi-0.2.0.dist-info/licenses/NOTICE
kakashi-0.2.0.dist-info/METADATA
kakashi-0.2.0.dist-info/WHEEL
kakashi-0.2.0.dist-info/entry_points.txt
kakashi-0.2.0.dist-info/top_level.txt
kakashi-0.2.0.dist-info/RECORD
