Metadata-Version: 2.4
Name: kakashi
Version: 0.2.0
Summary: High-performance logging utility for Python applications with advanced features
Home-page: https://github.com/IntegerAlex/kakashi
Author: Akshat Kotpalliwar
Author-email: Akshat Kotpalliwar <akshatkot@gmail.com>
Maintainer-email: Akshat Kotpalliwar <akshatkot@gmail.com>
License-Expression: LGPL-2.1
Project-URL: Homepage, https://github.com/IntegerAlex/kakashi
Project-URL: Repository, https://github.com/IntegerAlex/kakashi
Project-URL: Documentation, https://github.com/IntegerAlex/kakashi/wiki
Project-URL: Bug Reports, https://github.com/IntegerAlex/kakashi/issues
Keywords: logging,logger,fastapi,middleware,colored-logs,performance,singleton,rotation
Classifier: Development Status :: 4 - Beta
Classifier: Intended Audience :: Developers
Classifier: Operating System :: OS Independent
Classifier: Programming Language :: Python :: 3
Classifier: Programming Language :: Python :: 3.7
Classifier: Programming Language :: Python :: 3.8
Classifier: Programming Language :: Python :: 3.9
Classifier: Programming Language :: Python :: 3.10
Classifier: Programming Language :: Python :: 3.11
Classifier: Programming Language :: Python :: 3.12
Classifier: Topic :: Software Development :: Libraries :: Python Modules
Classifier: Topic :: System :: Logging
Classifier: Topic :: Internet :: WWW/HTTP :: WSGI :: Middleware
Requires-Python: >=3.7
License-File: LICENSE
License-File: NOTICE
Provides-Extra: fastapi
Requires-Dist: fastapi>=0.68.0; extra == "fastapi"
Requires-Dist: starlette>=0.14.0; extra == "fastapi"
Provides-Extra: flask
Requires-Dist: flask>=1.0.0; extra == "flask"
Provides-Extra: django
Requires-Dist: django>=3.0.0; extra == "django"
Provides-Extra: web
Requires-Dist: fastapi>=0.68.0; extra == "web"
Requires-Dist: starlette>=0.14.0; extra == "web"
Requires-Dist: flask>=1.0.0; extra == "web"
Requires-Dist: django>=3.0.0; extra == "web"
Provides-Extra: gui
Requires-Dist: tkinter; python_version >= "3.0" and extra == "gui"
Provides-Extra: dev
Requires-Dist: pytest>=6.0; extra == "dev"
Requires-Dist: pytest-asyncio>=0.18.0; extra == "dev"
Requires-Dist: black>=21.0.0; extra == "dev"
Requires-Dist: flake8>=3.8.0; extra == "dev"
Requires-Dist: mypy>=0.910; extra == "dev"
Requires-Dist: pre-commit>=2.15.0; extra == "dev"
Requires-Dist: build>=0.8.0; extra == "dev"
Requires-Dist: twine>=4.0.0; extra == "dev"
Provides-Extra: performance
Requires-Dist: orjson>=3.8.0; extra == "performance"
Requires-Dist: uvloop>=0.17.0; sys_platform != "win32" and extra == "performance"
Provides-Extra: all
Requires-Dist: fastapi>=0.68.0; extra == "all"
Requires-Dist: starlette>=0.14.0; extra == "all"
Requires-Dist: flask>=1.0.0; extra == "all"
Requires-Dist: django>=3.0.0; extra == "all"
Requires-Dist: orjson>=3.8.0; extra == "all"
Requires-Dist: uvloop>=0.17.0; sys_platform != "win32" and extra == "all"
Dynamic: author
Dynamic: home-page
Dynamic: license-file
Dynamic: requires-python
